islandora7_rest/IslandoraClient.py
islandora7_rest/__init__.py
islandora7_rest/config.py
islandora7_rest/ku/IslandoraClientKU.py
islandora7_rest/ku/__init__.py
islandora7_rest-3.0.4.dist-info/LICENSE.txt
islandora7_rest-3.0.4.dist-info/METADATA
islandora7_rest-3.0.4.dist-info/WHEEL
islandora7_rest-3.0.4.dist-info/top_level.txt
islandora7_rest-3.0.4.dist-info/RECORD
