Metadata-Version: 2.1
Name: islandora7-rest
Version: 3.0.4
Summary: Python client for discoverygarden/islandora_rest (for Islandora 7)
Home-page: https://github.com/kulibraries/islandora7-rest
Author: Jeremy Keeler <jkeeler@ku.edu>, Tom Shorock <shorock@ku.edu>
License: UNKNOWN
Platform: UNKNOWN
Classifier: Programming Language :: Python :: 3
Classifier: License :: OSI Approved :: BSD License
Classifier: Operating System :: OS Independent
Requires-Python: >=3
Requires-Dist: python-dotenv
Requires-Dist: requests (<3,>=2.5)
